[
  {
    "title": "Mutsuz Son",
    "image": "mutsuzson.jpg",
    "link": "https://youtu.be/2fWPXNPNpb8?si=nTgYWa4J_mneCxvN"
  },
  {
    "title": "İçimdeki Ölü",
    "image": "içimdekiölü.jpg",
    "link": "https://youtu.be/d75jhf2F3ko?si=vQ4tXQyWqhB-ijKq"
  },
  {
    "title": "Hala Aynı Gölge",
    "image": "halaaynıgölge.jpg",
    "link": "https://youtu.be/FElSpvfbCRI?si=9jink9IsrWNXuSzg"
  },
  {
    "title": "Yoksun İşte",
    "image": "yoksunişte.jpg",
    "link": "https://youtu.be/XFsK9wse1cs?si=U6IYGHWjdaAQk8gz"
  },
  {
    "title": "İçimde Ölürken",
    "image": "içimdeölürken.jpg",
    "link": "https://youtu.be/KaP7S648cVE?si=n5cfAM-goec7BQdu"
  }
]
